atomshields
tests
