Metadata-Version: 1.2
Name: atomshields
Version: 1.2.0
Summary: Security testing framework for repositories and source code.
Home-page: https://github.com/ElevenPaths/AtomShields
Author: ElevenPaths
Author-email: diego.fernandez@11paths.com, david.amrani@11paths.com
License: Apache 2.0
Download-URL: https://github.com/ElevenPaths/AtomShields/tarball/1.2.0
Project-URL: Source Code, https://github.com/ElevenPaths/AtomShields
Project-URL: Documentation, https://atomshields.readthedocs.io
Keywords: security,source code,analysis
Platform: UNKNOWN
Classifier: Development Status :: 4 - Beta
Classifier: Intended Audience :: Developers
Classifier: Intended Audience :: Other Audience
Classifier: License :: OSI Approved :: Apache Software License
Classifier: Natural Language :: English
Classifier: Operating System :: OS Independent
Classifier: Programming Language :: Python :: 2.7
Classifier: Topic :: Software Development :: Libraries :: Python Modules
Classifier: Topic :: Software Development :: Quality Assurance
Classifier: Topic :: Software Development :: Testing
